.gitignore
CHANGES.md
LICENSE
MANIFEST.in
README.md
pyproject.toml
requirements.txt
setup.py
./.coverage
./.gitignore
./CHANGES.md
./LICENSE
./MANIFEST.in
./README.md
./cc-reporter
./coverage.xml
./pyproject.toml
./requirements.txt
./setup.py
./async_include/__pycache__/__init__.cpython-311.pyc
./async_include/__pycache__/checksum.cpython-311.pyc
./async_include/__pycache__/crypto.cpython-311.pyc
./async_include/__pycache__/urls.cpython-311.pyc
./async_include/__pycache__/views.cpython-311.pyc
./async_include/migrations/__pycache__/__init__.cpython-311.pyc
./async_include/templates/async_include/spinner.html
./async_include/templates/async_include/template_tag.html
./async_include/templates/async_include/template_tag.js
./async_include/templatetags/__pycache__/__init__.cpython-311.pyc
./async_include/templatetags/__pycache__/async_include.cpython-311.pyc
./async_include/templatetags/__pycache__/async_included.cpython-311.pyc
./async_include/tests/__pycache__/__init__.cpython-311.pyc
./async_include/tests/__pycache__/settings.cpython-311.pyc
./async_include/tests/__pycache__/test_templatetags.cpython-311.pyc
./async_include/tests/__pycache__/test_views.cpython-311.pyc
./async_include/tests/__pycache__/urls.cpython-311.pyc
./async_include/tests/resources/test.db
./async_include/tests/templates/test_async_include.html
./django_async_include.egg-info/PKG-INFO
./django_async_include.egg-info/SOURCES.txt
./django_async_include.egg-info/dependency_links.txt
./django_async_include.egg-info/requires.txt
./django_async_include.egg-info/top_level.txt
async_include/__init__.py
async_include/checksum.py
async_include/crypto.py
async_include/urls.py
async_include/views.py
async_include/migrations/__init__.py
async_include/templates/async_include/spinner.html
async_include/templates/async_include/template_tag.html
async_include/templates/async_include/template_tag.js
async_include/templatetags/__init__.py
async_include/templatetags/async_include.py
async_include/templatetags/async_included.py
async_include/tests/__init__.py
async_include/tests/manage.py
async_include/tests/settings.py
async_include/tests/test_templatetags.py
async_include/tests/test_views.py
async_include/tests/urls.py
django_async_include.egg-info/PKG-INFO
django_async_include.egg-info/SOURCES.txt
django_async_include.egg-info/dependency_links.txt
django_async_include.egg-info/requires.txt
django_async_include.egg-info/top_level.txt