Metadata-Version: 2.1
Name: django-async-include
Version: 0.7.0
Summary: A simple application for Django to include (and fetch) asynchronous templates
Home-page: https://github.com/diegojromerolopez/django-async-include
Author: Diego J. Romero López
Author-email: "Diego J. Romero López" <diegojromerolopez@gmail.com>
License: MIT
Project-URL: Homepage, https://github.com/diegojromerolopez/django-async-include
Project-URL: Issues, https://github.com/diegojromerolopez/django-async-include/issues
Keywords: django template asynchronous template_tag
Classifier: Programming Language :: Python :: Implementation :: CPython
Classifier: Programming Language :: Python :: Implementation :: PyPy
Classifier: Programming Language :: Python :: 3.7
Classifier: Programming Language :: Python :: 3.8
Classifier: Programming Language :: Python :: 3.9
Classifier: Programming Language :: Python :: 3.10
Classifier: Programming Language :: Python :: 3.11
Classifier: Programming Language :: Python :: 3.12
Classifier: Programming Language :: Python :: 3.13
Classifier: Topic :: Software Development :: Libraries
Classifier: Development Status :: 5 - Production/Stable
Classifier: License :: OSI Approved :: MIT License
Requires-Python: >=3.7
License-File: LICENSE
